{
	"Pages" : 
	[
		{
			"Height" : 3300,
			"PageNumber" : 1,
			"Width" : 2550,
			"Words" : 
			[
				{
					"Region" : 
					{
						"b" : 0,
						"l" : -1789432832,
						"r" : 0,
						"t" : -1569715513
					},
					"Value" : ""
				},
				{
					"Region" : 
					{
						"b" : 0,
						"l" : -1789432832,
						"r" : 0,
						"t" : -1569715513
					},
					"Value" : ""
				},
				{
					"Region" : 
					{
						"b" : 1058,
						"l" : 1014,
						"r" : 1058,
						"t" : 204
					},
					"Value" : "2"
				},
				{
					"Region" : 
					{
						"b" : 1115,
						"l" : 1070,
						"r" : 1115,
						"t" : 241
					},
					"Value" : "K)"
				},
				{
					"Region" : 
					{
						"b" : 1407,
						"l" : 1397,
						"r" : 1407,
						"t" : 216
					},
					"Value" : "-"
				},
				{
					"Region" : 
					{
						"b" : 1737,
						"l" : 1553,
						"r" : 1737,
						"t" : 207
					},
					"Value" : "Partner's"
				},
				{
					"Region" : 
					{
						"b" : 1872,
						"l" : 1753,
						"r" : 1872,
						"t" : 207
					},
					"Value" : "Share"
				},
				{
					"Region" : 
					{
						"b" : 1929,
						"l" : 1887,
						"r" : 1929,
						"t" : 207
					},
					"Value" : "of"
				},
				{
					"Region" : 
					{
						"b" : 2098,
						"l" : 1941,
						"r" : 2098,
						"t" : 207
					},
					"Value" : "Current"
				},
				{
					"Region" : 
					{
						"b" : 2206,
						"l" : 2110,
						"r" : 2206,
						"t" : 207
					},
					"Value" : "Year"
				},
				{
					"Region" : 
					{
						"b" : 2380,
						"l" : 2220,
						"r" : 2380,
						"t" : 207
					},
					"Value" : "Income,"
				},
				{
					"Region" : 
					{
						"b" : 1788,
						"l" : 1553,
						"r" : 1788,
						"t" : 262
					},
					"Value" : "Deductions"
				},
				{
					"Region" : 
					{
						"b" : 1964,
						"l" : 1816,
						"r" : 1964,
						"t" : 262
					},
					"Value" : "Credits"
				},
				{
					"Region" : 
					{
						"b" : 2066,
						"l" : 1992,
						"r" : 2066,
						"t" : 262
					},
					"Value" : "and"
				},
				{
					"Region" : 
					{
						"b" : 2198,
						"l" : 2082,
						"r" : 2198,
						"t" : 262
					},
					"Value" : "Other"
				},
				{
					"Region" : 
					{
						"b" : 2322,
						"l" : 2212,
						"r" : 2322,
						"t" : 262
					},
					"Value" : "Items"
				},
				{
					"Region" : 
					{
						"b" : 1383,
						"l" : 1375,
						"r" : 1383,
						"t" : 311
					},
					"Value" : "1"
				},
				{
					"Region" : 
					{
						"b" : 1524,
						"l" : 1428,
						"r" : 1524,
						"t" : 311
					},
					"Value" : "Ordinary"
				},
				{
					"Region" : 
					{
						"b" : 1630,
						"l" : 1533,
						"r" : 1630,
						"t" : 311
					},
					"Value" : "business"
				},
				{
					"Region" : 
					{
						"b" : 1717,
						"l" : 1640,
						"r" : 1717,
						"t" : 311
					},
					"Value" : "income"
				},
				{
					"Region" : 
					{
						"b" : 1786,
						"l" : 1726,
						"r" : 1786,
						"t" : 310
					},
					"Value" : "(loss)"
				},
				{
					"Region" : 
					{
						"b" : 1424,
						"l" : 1421,
						"r" : 1424,
						"t" : 349
					},
					"Value" : "."
				},
				{
					"Region" : 
					{
						"b" : 1424,
						"l" : 1421,
						"r" : 1424,
						"t" : 359
					},
					"Value" : "|"
				},
				{
					"Region" : 
					{
						"b" : 1948,
						"l" : 1923,
						"r" : 1948,
						"t" : 311
					},
					"Value" : "15"
				},
				{
					"Region" : 
					{
						"b" : 2064,
						"l" : 1986,
						"r" : 2064,
						"t" : 311
					},
					"Value" : "Credits"
				},
				{
					"Region" : 
					{
						"b" : 1386,
						"l" : 1373,
						"r" : 1386,
						"t" : 404
					},
					"Value" : "2"
				},
				{
					"Region" : 
					{
						"b" : 1466,
						"l" : 1429,
						"r" : 1466,
						"t" : 403
					},
					"Value" : "Net"
				},
				{
					"Region" : 
					{
						"b" : 1535,
						"l" : 1475,
						"r" : 1535,
						"t" : 403
					},
					"Value" : "rental"
				},
				{
					"Region" : 
					{
						"b" : 1584,
						"l" : 1546,
						"r" : 1584,
						"t" : 403
					},
					"Value" : "real"
				},
				{
					"Region" : 
					{
						"b" : 1661,
						"l" : 1594,
						"r" : 1661,
						"t" : 404
					},
					"Value" : "estate"
				},
				{
					"Region" : 
					{
						"b" : 1749,
						"l" : 1670,
						"r" : 1749,
						"t" : 403
					},
					"Value" : "income"
				},
				{
					"Region" : 
					{
						"b" : 1818,
						"l" : 1758,
						"r" : 1818,
						"t" : 402
					},
					"Value" : "(loss)"
				},
				{
					"Region" : 
					{
						"b" : 1386,
						"l" : 1374,
						"r" : 1386,
						"t" : 506
					},
					"Value" : "3"
				},
				{
					"Region" : 
					{
						"b" : 1491,
						"l" : 1428,
						"r" : 1491,
						"t" : 506
					},
					"Value" : "Other"
				},
				{
					"Region" : 
					{
						"b" : 1532,
						"l" : 1499,
						"r" : 1532,
						"t" : 507
					},
					"Value" : "net"
				},
				{
					"Region" : 
					{
						"b" : 1601,
						"l" : 1541,
						"r" : 1601,
						"t" : 506
					},
					"Value" : "rental"
				},
				{
					"Region" : 
					{
						"b" : 1690,
						"l" : 1612,
						"r" : 1690,
						"t" : 506
					},
					"Value" : "income"
				},
				{
					"Region" : 
					{
						"b" : 1759,
						"l" : 1699,
						"r" : 1759,
						"t" : 505
					},
					"Value" : "(loss)"
				},
				{
					"Region" : 
					{
						"b" : 1387,
						"l" : 1373,
						"r" : 1387,
						"t" : 606
					},
					"Value" : "4"
				},
				{
					"Region" : 
					{
						"b" : 1559,
						"l" : 1429,
						"r" : 1559,
						"t" : 605
					},
					"Value" : "Guaranteed"
				},
				{
					"Region" : 
					{
						"b" : 1675,
						"l" : 1569,
						"r" : 1675,
						"t" : 606
					},
					"Value" : "payments"
				},
				{
					"Region" : 
					{
						"b" : 591,
						"l" : 355,
						"r" : 591,
						"t" : 603
					},
					"Value" : "Information"
				},
				{
					"Region" : 
					{
						"b" : 732,
						"l" : 606,
						"r" : 732,
						"t" : 603
					},
					"Value" : "About"
				},
				{
					"Region" : 
					{
						"b" : 808,
						"l" : 744,
						"r" : 808,
						"t" : 603
					},
					"Value" : "the"
				},
				{
					"Region" : 
					{
						"b" : 1037,
						"l" : 825,
						"r" : 1037,
						"t" : 603
					},
					"Value" : "Partnershi"
				},
				{
					"Region" : 
					{
						"b" : 211,
						"l" : 190,
						"r" : 211,
						"t" : 666
					},
					"Value" : "A"
				},
				{
					"Region" : 
					{
						"b" : 443,
						"l" : 282,
						"r" : 443,
						"t" : 666
					},
					"Value" : "Partnership's"
				},
				{
					"Region" : 
					{
						"b" : 566,
						"l" : 452,
						"r" : 566,
						"t" : 666
					},
					"Value" : "employer"
				},
				{
					"Region" : 
					{
						"b" : 729,
						"l" : 575,
						"r" : 729,
						"t" : 665
					},
					"Value" : "identification"
				},
				{
					"Region" : 
					{
						"b" : 834,
						"l" : 740,
						"r" : 834,
						"t" : 666
					},
					"Value" : "number"
				},
				{
					"Region" : 
					{
						"b" : 1386,
						"l" : 1374,
						"r" : 1386,
						"t" : 705
					},
					"Value" : "5"
				},
				{
					"Region" : 
					{
						"b" : 1511,
						"l" : 1430,
						"r" : 1511,
						"t" : 705
					},
					"Value" : "Interest"
				},
				{
					"Region" : 
					{
						"b" : 1599,
						"l" : 1521,
						"r" : 1599,
						"t" : 705
					},
					"Value" : "Income"
				},
				{
					"Region" : 
					{
						"b" : 1424,
						"l" : 1421,
						"r" : 1424,
						"t" : 738
					},
					"Value" : "I"
				},
				{
					"Region" : 
					{
						"b" : 1859,
						"l" : 1770,
						"r" : 1859,
						"t" : 758
					},
					"Value" : "1,046"
				},
				{
					"Region" : 
					{
						"b" : 209,
						"l" : 193,
						"r" : 209,
						"t" : 758
					},
					"Value" : "B"
				},
				{
					"Region" : 
					{
						"b" : 443,
						"l" : 282,
						"r" : 443,
						"t" : 758
					},
					"Value" : "Partnership's"
				},
				{
					"Region" : 
					{
						"b" : 527,
						"l" : 453,
						"r" : 527,
						"t" : 763
					},
					"Value" : "name,"
				},
				{
					"Region" : 
					{
						"b" : 643,
						"l" : 538,
						"r" : 643,
						"t" : 758
					},
					"Value" : "address,"
				},
				{
					"Region" : 
					{
						"b" : 701,
						"l" : 654,
						"r" : 701,
						"t" : 758
					},
					"Value" : "city,"
				},
				{
					"Region" : 
					{
						"b" : 777,
						"l" : 712,
						"r" : 777,
						"t" : 758
					},
					"Value" : "state,"
				},
				{
					"Region" : 
					{
						"b" : 832,
						"l" : 788,
						"r" : 832,
						"t" : 758
					},
					"Value" : "and"
				},
				{
					"Region" : 
					{
						"b" : 885,
						"l" : 842,
						"r" : 885,
						"t" : 758
					},
					"Value" : "ZIP"
				},
				{
					"Region" : 
					{
						"b" : 953,
						"l" : 894,
						"r" : 953,
						"t" : 758
					},
					"Value" : "code"
				},
				{
					"Region" : 
					{
						"b" : 449,
						"l" : 277,
						"r" : 449,
						"t" : 874
					},
					"Value" : "—"
				},
				{
					"Region" : 
					{
						"b" : 1393,
						"l" : 1367,
						"r" : 1393,
						"t" : 797
					},
					"Value" : "6a"
				},
				{
					"Region" : 
					{
						"b" : 1524,
						"l" : 1428,
						"r" : 1524,
						"t" : 797
					},
					"Value" : "Ordinary"
				},
				{
					"Region" : 
					{
						"b" : 1638,
						"l" : 1532,
						"r" : 1638,
						"t" : 797
					},
					"Value" : "dividends"
				},
				{
					"Region" : 
					{
						"b" : 1394,
						"l" : 1366,
						"r" : 1394,
						"t" : 876
					},
					"Value" : "6b"
				},
				{
					"Region" : 
					{
						"b" : 1526,
						"l" : 1428,
						"r" : 1526,
						"t" : 876
					},
					"Value" : "Qualified"
				},
				{
					"Region" : 
					{
						"b" : 1641,
						"l" : 1535,
						"r" : 1641,
						"t" : 876
					},
					"Value" : "dividends"
				},
				{
					"Region" : 
					{
						"b" : 1948,
						"l" : 1923,
						"r" : 1948,
						"t" : 506
					},
					"Value" : "16"
				},
				{
					"Region" : 
					{
						"b" : 2069,
						"l" : 1987,
						"r" : 2069,
						"t" : 506
					},
					"Value" : "Foreign"
				},
				{
					"Region" : 
					{
						"b" : 2213,
						"l" : 2078,
						"r" : 2213,
						"t" : 506
					},
					"Value" : "transactions"
				},
				{
					"Region" : 
					{
						"b" : 2420,
						"l" : 2311,
						"r" : 2420,
						"t" : 566
					},
					"Value" : "12,521"
				},
				{
					"Region" : 
					{
						"b" : 2358,
						"l" : 2311,
						"r" : 2358,
						"t" : 666
					},
					"Value" : "11,"
				},
				{
					"Region" : 
					{
						"b" : 2419,
						"l" : 2367,
						"r" : 2419,
						"t" : 667
					},
					"Value" : "475"
				},
				{
					"Region" : 
					{
						"b" : 2358,
						"l" : 2330,
						"r" : 2358,
						"t" : 758
					},
					"Value" : "1,"
				},
				{
					"Region" : 
					{
						"b" : 2419,
						"l" : 2368,
						"r" : 2419,
						"t" : 759
					},
					"Value" : "046"
				},
				{
					"Region" : 
					{
						"b" : 2419,
						"l" : 2330,
						"r" : 2419,
						"t" : 836
					},
					"Value" : "1,045"
				},
				{
					"Region" : 
					{
						"b" : 2419,
						"l" : 2386,
						"r" : 2419,
						"t" : 917
					},
					"Value" : "37"
				},
				{
					"Region" : 
					{
						"b" : 1386,
						"l" : 1374,
						"r" : 1386,
						"t" : 995
					},
					"Value" : "7"
				},
				{
					"Region" : 
					{
						"b" : 1531,
						"l" : 1429,
						"r" : 1531,
						"t" : 994
					},
					"Value" : "Royalties"
				},
				{
					"Region" : 
					{
						"b" : 209,
						"l" : 192,
						"r" : 209,
						"t" : 1009
					},
					"Value" : "C"
				},
				{
					"Region" : 
					{
						"b" : 325,
						"l" : 283,
						"r" : 325,
						"t" : 1009
					},
					"Value" : "IRS"
				},
				{
					"Region" : 
					{
						"b" : 419,
						"l" : 336,
						"r" : 419,
						"t" : 1009
					},
					"Value" : "Center"
				},
				{
					"Region" : 
					{
						"b" : 501,
						"l" : 426,
						"r" : 501,
						"t" : 1010
					},
					"Value" : "where"
				},
				{
					"Region" : 
					{
						"b" : 650,
						"l" : 512,
						"r" : 650,
						"t" : 1010
					},
					"Value" : "partnership"
				},
				{
					"Region" : 
					{
						"b" : 708,
						"l" : 659,
						"r" : 708,
						"t" : 1009
					},
					"Value" : "filed"
				},
				{
					"Region" : 
					{
						"b" : 789,
						"l" : 719,
						"r" : 789,
						"t" : 1010
					},
					"Value" : "return"
				},
				{
					"Region" : 
					{
						"b" : 389,
						"l" : 283,
						"r" : 389,
						"t" : 1056
					},
					"Value" : "OGDEN,"
				},
				{
					"Region" : 
					{
						"b" : 451,
						"l" : 415,
						"r" : 451,
						"t" : 1056
					},
					"Value" : "UT"
				},
				{
					"Region" : 
					{
						"b" : 1386,
						"l" : 1374,
						"r" : 1386,
						"t" : 1094
					},
					"Value" : "8"
				},
				{
					"Region" : 
					{
						"b" : 1466,
						"l" : 1429,
						"r" : 1466,
						"t" : 1093
					},
					"Value" : "Net"
				},
				{
					"Region" : 
					{
						"b" : 1587,
						"l" : 1474,
						"r" : 1587,
						"t" : 1093
					},
					"Value" : "short-term"
				},
				{
					"Region" : 
					{
						"b" : 1666,
						"l" : 1595,
						"r" : 1666,
						"t" : 1093
					},
					"Value" : "capital"
				},
				{
					"Region" : 
					{
						"b" : 1721,
						"l" : 1675,
						"r" : 1721,
						"t" : 1093
					},
					"Value" : "gain"
				},
				{
					"Region" : 
					{
						"b" : 1791,
						"l" : 1731,
						"r" : 1791,
						"t" : 1092
					},
					"Value" : "(loss)"
				},
				{
					"Region" : 
					{
						"b" : 1424,
						"l" : 1421,
						"r" : 1424,
						"t" : 1127
					},
					"Value" : "I"
				},
				{
					"Region" : 
					{
						"b" : 0,
						"l" : -1789432832,
						"r" : 0,
						"t" : -1569715513
					},
					"Value" : ""
				},
				{
					"Region" : 
					{
						"b" : 209,
						"l" : 193,
						"r" : 209,
						"t" : 1131
					},
					"Value" : "D"
				},
				{
					"Region" : 
					{
						"b" : 393,
						"l" : 273,
						"r" : 393,
						"t" : 1123
					},
					"Value" : "DCheck"
				},
				{
					"Region" : 
					{
						"b" : 414,
						"l" : 402,
						"r" : 414,
						"t" : 1133
					},
					"Value" : "if"
				},
				{
					"Region" : 
					{
						"b" : 459,
						"l" : 421,
						"r" : 459,
						"t" : 1133
					},
					"Value" : "this"
				},
				{
					"Region" : 
					{
						"b" : 485,
						"l" : 469,
						"r" : 485,
						"t" : 1133
					},
					"Value" : "is"
				},
				{
					"Region" : 
					{
						"b" : 506,
						"l" : 493,
						"r" : 506,
						"t" : 1137
					},
					"Value" : "a"
				},
				{
					"Region" : 
					{
						"b" : 598,
						"l" : 515,
						"r" : 598,
						"t" : 1133
					},
					"Value" : "publicly"
				},
				{
					"Region" : 
					{
						"b" : 675,
						"l" : 606,
						"r" : 675,
						"t" : 1133
					},
					"Value" : "traded"
				},
				{
					"Region" : 
					{
						"b" : 809,
						"l" : 685,
						"r" : 809,
						"t" : 1133
					},
					"Value" : "partnership"
				},
				{
					"Region" : 
					{
						"b" : 882,
						"l" : 818,
						"r" : 882,
						"t" : 1132
					},
					"Value" : "(PTP)"
				},
				{
					"Region" : 
					{
						"b" : 1948,
						"l" : 1923,
						"r" : 1948,
						"t" : 1186
					},
					"Value" : "17"
				},
				{
					"Region" : 
					{
						"b" : 2104,
						"l" : 1985,
						"r" : 2104,
						"t" : 1186
					},
					"Value" : "Alternative"
				},
				{
					"Region" : 
					{
						"b" : 2211,
						"l" : 2113,
						"r" : 2211,
						"t" : 1186
					},
					"Value" : "minimum"
				},
				{
					"Region" : 
					{
						"b" : 2252,
						"l" : 2219,
						"r" : 2252,
						"t" : 1187
					},
					"Value" : "tax"
				},
				{
					"Region" : 
					{
						"b" : 2327,
						"l" : 2260,
						"r" : 2327,
						"t" : 1185
					},
					"Value" : "(AMT)"
				},
				{
					"Region" : 
					{
						"b" : 2394,
						"l" : 2337,
						"r" : 2394,
						"t" : 1186
					},
					"Value" : "items"
				},
				{
					"Region" : 
					{
						"b" : 556,
						"l" : 354,
						"r" : 556,
						"t" : 1192
					},
					"Value" : "Information"
				},
				{
					"Region" : 
					{
						"b" : 677,
						"l" : 569,
						"r" : 677,
						"t" : 1193
					},
					"Value" : "About"
				},
				{
					"Region" : 
					{
						"b" : 743,
						"l" : 688,
						"r" : 743,
						"t" : 1193
					},
					"Value" : "the"
				},
				{
					"Region" : 
					{
						"b" : 887,
						"l" : 757,
						"r" : 887,
						"t" : 1193
					},
					"Value" : "Partner"
				},
				{
					"Region" : 
					{
						"b" : 1393,
						"l" : 1366,
						"r" : 1393,
						"t" : 1186
					},
					"Value" : "9a"
				},
				{
					"Region" : 
					{
						"b" : 1466,
						"l" : 1429,
						"r" : 1466,
						"t" : 1186
					},
					"Value" : "Net"
				},
				{
					"Region" : 
					{
						"b" : 1579,
						"l" : 1475,
						"r" : 1579,
						"t" : 1186
					},
					"Value" : "long-term"
				},
				{
					"Region" : 
					{
						"b" : 1658,
						"l" : 1587,
						"r" : 1658,
						"t" : 1186
					},
					"Value" : "capital"
				},
				{
					"Region" : 
					{
						"b" : 1713,
						"l" : 1667,
						"r" : 1713,
						"t" : 1186
					},
					"Value" : "gain"
				},
				{
					"Region" : 
					{
						"b" : 1783,
						"l" : 1723,
						"r" : 1783,
						"t" : 1185
					},
					"Value" : "(loss)"
				},
				{
					"Region" : 
					{
						"b" : 1798,
						"l" : 1751,
						"r" : 1798,
						"t" : 1251
					},
					"Value" : "11,"
				},
				{
					"Region" : 
					{
						"b" : 1859,
						"l" : 1807,
						"r" : 1859,
						"t" : 1252
					},
					"Value" : "475"
				},
				{
					"Region" : 
					{
						"b" : 206,
						"l" : 192,
						"r" : 206,
						"t" : 1253
					},
					"Value" : "E"
				},
				{
					"Region" : 
					{
						"b" : 391,
						"l" : 282,
						"r" : 391,
						"t" : 1251
					},
					"Value" : "Partner's"
				},
				{
					"Region" : 
					{
						"b" : 525,
						"l" : 402,
						"r" : 525,
						"t" : 1250
					},
					"Value" : "identifying"
				},
				{
					"Region" : 
					{
						"b" : 630,
						"l" : 536,
						"r" : 630,
						"t" : 1251
					},
					"Value" : "number"
				},
				{
					"Region" : 
					{
						"b" : 1394,
						"l" : 1366,
						"r" : 1394,
						"t" : 1290
					},
					"Value" : "9b"
				},
				{
					"Region" : 
					{
						"b" : 1557,
						"l" : 1428,
						"r" : 1557,
						"t" : 1290
					},
					"Value" : "Collectibles"
				},
				{
					"Region" : 
					{
						"b" : 1631,
						"l" : 1566,
						"r" : 1631,
						"t" : 1289
					},
					"Value" : "(28%)"
				},
				{
					"Region" : 
					{
						"b" : 1685,
						"l" : 1639,
						"r" : 1685,
						"t" : 1290
					},
					"Value" : "gain"
				},
				{
					"Region" : 
					{
						"b" : 1755,
						"l" : 1695,
						"r" : 1755,
						"t" : 1289
					},
					"Value" : "(loss)"
				},
				{
					"Region" : 
					{
						"b" : 204,
						"l" : 192,
						"r" : 204,
						"t" : 1345
					},
					"Value" : "F"
				},
				{
					"Region" : 
					{
						"b" : 391,
						"l" : 282,
						"r" : 391,
						"t" : 1343
					},
					"Value" : "Partner's"
				},
				{
					"Region" : 
					{
						"b" : 476,
						"l" : 402,
						"r" : 476,
						"t" : 1348
					},
					"Value" : "name,"
				},
				{
					"Region" : 
					{
						"b" : 591,
						"l" : 487,
						"r" : 591,
						"t" : 1343
					},
					"Value" : "address,"
				},
				{
					"Region" : 
					{
						"b" : 649,
						"l" : 602,
						"r" : 649,
						"t" : 1343
					},
					"Value" : "city,"
				},
				{
					"Region" : 
					{
						"b" : 726,
						"l" : 660,
						"r" : 726,
						"t" : 1343
					},
					"Value" : "state,"
				},
				{
					"Region" : 
					{
						"b" : 781,
						"l" : 737,
						"r" : 781,
						"t" : 1343
					},
					"Value" : "and"
				},
				{
					"Region" : 
					{
						"b" : 833,
						"l" : 791,
						"r" : 833,
						"t" : 1343
					},
					"Value" : "ZIP"
				},
				{
					"Region" : 
					{
						"b" : 902,
						"l" : 843,
						"r" : 902,
						"t" : 1343
					},
					"Value" : "code"
				},
				{
					"Region" : 
					{
						"b" : 1393,
						"l" : 1366,
						"r" : 1393,
						"t" : 1383
					},
					"Value" : "9c"
				},
				{
					"Region" : 
					{
						"b" : 1578,
						"l" : 1429,
						"r" : 1578,
						"t" : 1382
					},
					"Value" : "Unrecaptured"
				},
				{
					"Region" : 
					{
						"b" : 1665,
						"l" : 1588,
						"r" : 1665,
						"t" : 1382
					},
					"Value" : "section"
				},
				{
					"Region" : 
					{
						"b" : 1729,
						"l" : 1676,
						"r" : 1729,
						"t" : 1382
					},
					"Value" : "1250"
				},
				{
					"Region" : 
					{
						"b" : 1783,
						"l" : 1737,
						"r" : 1783,
						"t" : 1382
					},
					"Value" : "gain"
				},
				{
					"Region" : 
					{
						"b" : 1393,
						"l" : 1368,
						"r" : 1393,
						"t" : 1501
					},
					"Value" : "10"
				},
				{
					"Region" : 
					{
						"b" : 1466,
						"l" : 1429,
						"r" : 1466,
						"t" : 1501
					},
					"Value" : "Net"
				},
				{
					"Region" : 
					{
						"b" : 1552,
						"l" : 1474,
						"r" : 1552,
						"t" : 1501
					},
					"Value" : "section"
				},
				{
					"Region" : 
					{
						"b" : 1612,
						"l" : 1563,
						"r" : 1612,
						"t" : 1501
					},
					"Value" : "1231"
				},
				{
					"Region" : 
					{
						"b" : 1670,
						"l" : 1624,
						"r" : 1670,
						"t" : 1501
					},
					"Value" : "gain"
				},
				{
					"Region" : 
					{
						"b" : 1740,
						"l" : 1680,
						"r" : 1740,
						"t" : 1500
					},
					"Value" : "(loss)"
				},
				{
					"Region" : 
					{
						"b" : 1948,
						"l" : 1923,
						"r" : 1948,
						"t" : 1503
					},
					"Value" : "18"
				},
				{
					"Region" : 
					{
						"b" : 2116,
						"l" : 1985,
						"r" : 2116,
						"t" : 1504
					},
					"Value" : "Tax-exempt"
				},
				{
					"Region" : 
					{
						"b" : 2203,
						"l" : 2125,
						"r" : 2203,
						"t" : 1504
					},
					"Value" : "income"
				},
				{
					"Region" : 
					{
						"b" : 2251,
						"l" : 2211,
						"r" : 2251,
						"t" : 1504
					},
					"Value" : "and"
				},
				{
					"Region" : 
					{
						"b" : 2142,
						"l" : 1987,
						"r" : 2142,
						"t" : 1547
					},
					"Value" : "nondeductible"
				},
				{
					"Region" : 
					{
						"b" : 2256,
						"l" : 2150,
						"r" : 2256,
						"t" : 1551
					},
					"Value" : "expenses"
				},
				{
					"Region" : 
					{
						"b" : 1390,
						"l" : 1368,
						"r" : 1390,
						"t" : 1610
					},
					"Value" : "11"
				},
				{
					"Region" : 
					{
						"b" : 1491,
						"l" : 1428,
						"r" : 1491,
						"t" : 1610
					},
					"Value" : "Other"
				},
				{
					"Region" : 
					{
						"b" : 1577,
						"l" : 1499,
						"r" : 1577,
						"t" : 1610
					},
					"Value" : "income"
				},
				{
					"Region" : 
					{
						"b" : 1646,
						"l" : 1586,
						"r" : 1646,
						"t" : 1609
					},
					"Value" : "(loss)"
				},
				{
					"Region" : 
					{
						"b" : 0,
						"l" : -1789432832,
						"r" : 0,
						"t" : -1569715513
					},
					"Value" : ""
				},
				{
					"Region" : 
					{
						"b" : 0,
						"l" : -1789432832,
						"r" : 0,
						"t" : -1569715513
					},
					"Value" : ""
				},
				{
					"Region" : 
					{
						"b" : 0,
						"l" : -1789432832,
						"r" : 0,
						"t" : -1569715513
					},
					"Value" : ""
				},
				{
					"Region" : 
					{
						"b" : 0,
						"l" : -1789432832,
						"r" : 0,
						"t" : -1569715513
					},
					"Value" : ""
				},
				{
					"Region" : 
					{
						"b" : 0,
						"l" : -1789432832,
						"r" : 0,
						"t" : -1569715513
					},
					"Value" : ""
				},
				{
					"Region" : 
					{
						"b" : 1948,
						"l" : 1923,
						"r" : 1948,
						"t" : 1869
					},
					"Value" : "19"
				},
				{
					"Region" : 
					{
						"b" : 2124,
						"l" : 1978,
						"r" : 2124,
						"t" : 1869
					},
					"Value" : "IDistributions"
				},
				{
					"Region" : 
					{
						"b" : 1945,
						"l" : 1925,
						"r" : 1945,
						"t" : 1925
					},
					"Value" : "A"
				},
				{
					"Region" : 
					{
						"b" : 2419,
						"l" : 2310,
						"r" : 2419,
						"t" : 1924
					},
					"Value" : "20,374"
				},
				{
					"Region" : 
					{
						"b" : 1393,
						"l" : 1368,
						"r" : 1393,
						"t" : 1923
					},
					"Value" : "12"
				},
				{
					"Region" : 
					{
						"b" : 1510,
						"l" : 1428,
						"r" : 1510,
						"t" : 1922
					},
					"Value" : "Section"
				},
				{
					"Region" : 
					{
						"b" : 1560,
						"l" : 1521,
						"r" : 1560,
						"t" : 1922
					},
					"Value" : "179"
				},
				{
					"Region" : 
					{
						"b" : 1675,
						"l" : 1568,
						"r" : 1675,
						"t" : 1922
					},
					"Value" : "deduction"
				},
				{
					"Region" : 
					{
						"b" : 1393,
						"l" : 1368,
						"r" : 1393,
						"t" : 2015
					},
					"Value" : "13"
				},
				{
					"Region" : 
					{
						"b" : 1491,
						"l" : 1428,
						"r" : 1491,
						"t" : 2014
					},
					"Value" : "Other"
				},
				{
					"Region" : 
					{
						"b" : 1619,
						"l" : 1498,
						"r" : 1619,
						"t" : 2014
					},
					"Value" : "deductions"
				},
				{
					"Region" : 
					{
						"b" : 1859,
						"l" : 1770,
						"r" : 1859,
						"t" : 2102
					},
					"Value" : "1,045"
				},
				{
					"Region" : 
					{
						"b" : 1859,
						"l" : 1826,
						"r" : 1859,
						"t" : 2186
					},
					"Value" : "37"
				},
				{
					"Region" : 
					{
						"b" : 1394,
						"l" : 1368,
						"r" : 1394,
						"t" : 2315
					},
					"Value" : "14"
				},
				{
					"Region" : 
					{
						"b" : 1615,
						"l" : 1428,
						"r" : 1615,
						"t" : 2314
					},
					"Value" : "Self-employment"
				},
				{
					"Region" : 
					{
						"b" : 1718,
						"l" : 1623,
						"r" : 1718,
						"t" : 2314
					},
					"Value" : "earnings"
				},
				{
					"Region" : 
					{
						"b" : 1787,
						"l" : 1727,
						"r" : 1787,
						"t" : 2313
					},
					"Value" : "(loss)"
				},
				{
					"Region" : 
					{
						"b" : 208,
						"l" : 191,
						"r" : 208,
						"t" : 1649
					},
					"Value" : "G"
				},
				{
					"Region" : 
					{
						"b" : 410,
						"l" : 273,
						"r" : 410,
						"t" : 1637
					},
					"Value" : "EIGeneral"
				},
				{
					"Region" : 
					{
						"b" : 500,
						"l" : 421,
						"r" : 500,
						"t" : 1650
					},
					"Value" : "partner"
				},
				{
					"Region" : 
					{
						"b" : 529,
						"l" : 507,
						"r" : 529,
						"t" : 1653
					},
					"Value" : "or"
				},
				{
					"Region" : 
					{
						"b" : 581,
						"l" : 538,
						"r" : 581,
						"t" : 1649
					},
					"Value" : "LLC"
				},
				{
					"Region" : 
					{
						"b" : 902,
						"l" : 776,
						"r" : 902,
						"t" : 1637
					},
					"Value" : "ELimited"
				},
				{
					"Region" : 
					{
						"b" : 991,
						"l" : 912,
						"r" : 991,
						"t" : 1650
					},
					"Value" : "partner"
				},
				{
					"Region" : 
					{
						"b" : 1020,
						"l" : 998,
						"r" : 1020,
						"t" : 1653
					},
					"Value" : "or"
				},
				{
					"Region" : 
					{
						"b" : 1085,
						"l" : 1027,
						"r" : 1085,
						"t" : 1649
					},
					"Value" : "other"
				},
				{
					"Region" : 
					{
						"b" : 1137,
						"l" : 1093,
						"r" : 1137,
						"t" : 1649
					},
					"Value" : "LLC"
				},
				{
					"Region" : 
					{
						"b" : 913,
						"l" : 824,
						"r" : 913,
						"t" : 1686
					},
					"Value" : "member"
				},
				{
					"Region" : 
					{
						"b" : 520,
						"l" : 324,
						"r" : 520,
						"t" : 1686
					},
					"Value" : "member-manager"
				},
				{
					"Region" : 
					{
						"b" : 319,
						"l" : 273,
						"r" : 319,
						"t" : 1729
					},
					"Value" : "El"
				},
				{
					"Region" : 
					{
						"b" : 426,
						"l" : 324,
						"r" : 426,
						"t" : 1744
					},
					"Value" : "Domestic"
				},
				{
					"Region" : 
					{
						"b" : 514,
						"l" : 435,
						"r" : 514,
						"t" : 1745
					},
					"Value" : "partner"
				},
				{
					"Region" : 
					{
						"b" : 907,
						"l" : 776,
						"r" : 907,
						"t" : 1729
					},
					"Value" : "DForeign"
				},
				{
					"Region" : 
					{
						"b" : 996,
						"l" : 917,
						"r" : 996,
						"t" : 1745
					},
					"Value" : "partner"
				},
				{
					"Region" : 
					{
						"b" : 207,
						"l" : 192,
						"r" : 207,
						"t" : 1832
					},
					"Value" : "I1"
				},
				{
					"Region" : 
					{
						"b" : 340,
						"l" : 280,
						"r" : 340,
						"t" : 1832
					},
					"Value" : "What"
				},
				{
					"Region" : 
					{
						"b" : 394,
						"l" : 347,
						"r" : 394,
						"t" : 1833
					},
					"Value" : "type"
				},
				{
					"Region" : 
					{
						"b" : 423,
						"l" : 402,
						"r" : 423,
						"t" : 1832
					},
					"Value" : "of"
				},
				{
					"Region" : 
					{
						"b" : 490,
						"l" : 430,
						"r" : 490,
						"t" : 1832
					},
					"Value" : "entity"
				},
				{
					"Region" : 
					{
						"b" : 515,
						"l" : 499,
						"r" : 515,
						"t" : 1832
					},
					"Value" : "is"
				},
				{
					"Region" : 
					{
						"b" : 561,
						"l" : 523,
						"r" : 561,
						"t" : 1832
					},
					"Value" : "this"
				},
				{
					"Region" : 
					{
						"b" : 661,
						"l" : 571,
						"r" : 661,
						"t" : 1832
					},
					"Value" : "partner’?"
				},
				{
					"Region" : 
					{
						"b" : 1292,
						"l" : 1086,
						"r" : 1292,
						"t" : 1831
					},
					"Value" : "PARTNERSHIP"
				},
				{
					"Region" : 
					{
						"b" : 209,
						"l" : 192,
						"r" : 209,
						"t" : 1885
					},
					"Value" : "I2"
				},
				{
					"Region" : 
					{
						"b" : 295,
						"l" : 282,
						"r" : 295,
						"t" : 1885
					},
					"Value" : "If"
				},
				{
					"Region" : 
					{
						"b" : 340,
						"l" : 301,
						"r" : 340,
						"t" : 1885
					},
					"Value" : "this"
				},
				{
					"Region" : 
					{
						"b" : 428,
						"l" : 349,
						"r" : 428,
						"t" : 1886
					},
					"Value" : "partner"
				},
				{
					"Region" : 
					{
						"b" : 452,
						"l" : 436,
						"r" : 452,
						"t" : 1885
					},
					"Value" : "is"
				},
				{
					"Region" : 
					{
						"b" : 473,
						"l" : 461,
						"r" : 473,
						"t" : 1889
					},
					"Value" : "a"
				},
				{
					"Region" : 
					{
						"b" : 594,
						"l" : 483,
						"r" : 594,
						"t" : 1885
					},
					"Value" : "retirement"
				},
				{
					"Region" : 
					{
						"b" : 647,
						"l" : 603,
						"r" : 647,
						"t" : 1885
					},
					"Value" : "plan"
				},
				{
					"Region" : 
					{
						"b" : 903,
						"l" : 657,
						"r" : 903,
						"t" : 1884
					},
					"Value" : "(IRA/SEP/Keogh/etc.),"
				},
				{
					"Region" : 
					{
						"b" : 977,
						"l" : 913,
						"r" : 977,
						"t" : 1885
					},
					"Value" : "check"
				},
				{
					"Region" : 
					{
						"b" : 1034,
						"l" : 986,
						"r" : 1034,
						"t" : 1885
					},
					"Value" : "here"
				},
				{
					"Region" : 
					{
						"b" : 328,
						"l" : 281,
						"r" : 328,
						"t" : 1924
					},
					"Value" : "(see"
				},
				{
					"Region" : 
					{
						"b" : 472,
						"l" : 338,
						"r" : 472,
						"t" : 1924
					},
					"Value" : "instructions)"
				},
				{
					"Region" : 
					{
						"b" : 484,
						"l" : 481,
						"r" : 484,
						"t" : 1940
					},
					"Value" : "."
				},
				{
					"Region" : 
					{
						"b" : 505,
						"l" : 502,
						"r" : 505,
						"t" : 1940
					},
					"Value" : "."
				},
				{
					"Region" : 
					{
						"b" : 533,
						"l" : 530,
						"r" : 533,
						"t" : 1940
					},
					"Value" : "."
				},
				{
					"Region" : 
					{
						"b" : 1262,
						"l" : 1218,
						"r" : 1262,
						"t" : 1913
					},
					"Value" : "El"
				},
				{
					"Region" : 
					{
						"b" : 379,
						"l" : 282,
						"r" : 379,
						"t" : 1977
					},
					"Value" : "Partner‘s"
				},
				{
					"Region" : 
					{
						"b" : 449,
						"l" : 388,
						"r" : 449,
						"t" : 1977
					},
					"Value" : "share"
				},
				{
					"Region" : 
					{
						"b" : 478,
						"l" : 457,
						"r" : 478,
						"t" : 1977
					},
					"Value" : "of"
				},
				{
					"Region" : 
					{
						"b" : 546,
						"l" : 486,
						"r" : 546,
						"t" : 1977
					},
					"Value" : "profit,"
				},
				{
					"Region" : 
					{
						"b" : 605,
						"l" : 557,
						"r" : 605,
						"t" : 1977
					},
					"Value" : "loss,"
				},
				{
					"Region" : 
					{
						"b" : 655,
						"l" : 615,
						"r" : 655,
						"t" : 1977
					},
					"Value" : "and"
				},
				{
					"Region" : 
					{
						"b" : 735,
						"l" : 664,
						"r" : 735,
						"t" : 1977
					},
					"Value" : "capital"
				},
				{
					"Region" : 
					{
						"b" : 792,
						"l" : 745,
						"r" : 792,
						"t" : 1976
					},
					"Value" : "(see"
				},
				{
					"Region" : 
					{
						"b" : 942,
						"l" : 802,
						"r" : 942,
						"t" : 1976
					},
					"Value" : "instructions):"
				},
				{
					"Region" : 
					{
						"b" : 563,
						"l" : 444,
						"r" : 563,
						"t" : 2062
					},
					"Value" : "Beginning"
				},
				{
					"Region" : 
					{
						"b" : 1055,
						"l" : 974,
						"r" : 1055,
						"t" : 2062
					},
					"Value" : "Ending"
				},
				{
					"Region" : 
					{
						"b" : 339,
						"l" : 282,
						"r" : 339,
						"t" : 2104
					},
					"Value" : "Profit"
				},
				{
					"Region" : 
					{
						"b" : 669,
						"l" : 641,
						"r" : 669,
						"t" : 2102
					},
					"Value" : "0."
				},
				{
					"Region" : 
					{
						"b" : 769,
						"l" : 679,
						"r" : 769,
						"t" : 2102
					},
					"Value" : "0049*"
				},
				{
					"Region" : 
					{
						"b" : 1292,
						"l" : 1164,
						"r" : 1292,
						"t" : 2102
					},
					"Value" : "0.0049*"
				},
				{
					"Region" : 
					{
						"b" : 332,
						"l" : 282,
						"r" : 332,
						"t" : 2145
					},
					"Value" : "LOSS"
				},
				{
					"Region" : 
					{
						"b" : 669,
						"l" : 641,
						"r" : 669,
						"t" : 2144
					},
					"Value" : "0."
				},
				{
					"Region" : 
					{
						"b" : 769,
						"l" : 679,
						"r" : 769,
						"t" : 2144
					},
					"Value" : "0049*"
				},
				{
					"Region" : 
					{
						"b" : 1292,
						"l" : 1164,
						"r" : 1292,
						"t" : 2144
					},
					"Value" : "0.0049*"
				},
				{
					"Region" : 
					{
						"b" : 357,
						"l" : 281,
						"r" : 357,
						"t" : 2187
					},
					"Value" : "Capital"
				},
				{
					"Region" : 
					{
						"b" : 669,
						"l" : 641,
						"r" : 669,
						"t" : 2185
					},
					"Value" : "0."
				},
				{
					"Region" : 
					{
						"b" : 769,
						"l" : 679,
						"r" : 769,
						"t" : 2185
					},
					"Value" : "0049*"
				},
				{
					"Region" : 
					{
						"b" : 1292,
						"l" : 1164,
						"r" : 1292,
						"t" : 2185
					},
					"Value" : "0.0049*"
				},
				{
					"Region" : 
					{
						"b" : 379,
						"l" : 282,
						"r" : 379,
						"t" : 2277
					},
					"Value" : "Partner‘s"
				},
				{
					"Region" : 
					{
						"b" : 449,
						"l" : 388,
						"r" : 449,
						"t" : 2277
					},
					"Value" : "share"
				},
				{
					"Region" : 
					{
						"b" : 479,
						"l" : 457,
						"r" : 479,
						"t" : 2277
					},
					"Value" : "of"
				},
				{
					"Region" : 
					{
						"b" : 582,
						"l" : 487,
						"r" : 582,
						"t" : 2277
					},
					"Value" : "liabilities"
				},
				{
					"Region" : 
					{
						"b" : 610,
						"l" : 590,
						"r" : 610,
						"t" : 2278
					},
					"Value" : "at"
				},
				{
					"Region" : 
					{
						"b" : 667,
						"l" : 618,
						"r" : 667,
						"t" : 2281
					},
					"Value" : "year"
				},
				{
					"Region" : 
					{
						"b" : 721,
						"l" : 674,
						"r" : 721,
						"t" : 2277
					},
					"Value" : "end:"
				},
				{
					"Region" : 
					{
						"b" : 423,
						"l" : 282,
						"r" : 423,
						"t" : 2326
					},
					"Value" : "Nonrecourse"
				},
				{
					"Region" : 
					{
						"b" : 1231,
						"l" : 1142,
						"r" : 1231,
						"t" : 2324
					},
					"Value" : "7,420"
				},
				{
					"Region" : 
					{
						"b" : 379,
						"l" : 281,
						"r" : 379,
						"t" : 2363
					},
					"Value" : "Qualified"
				},
				{
					"Region" : 
					{
						"b" : 526,
						"l" : 389,
						"r" : 526,
						"t" : 2367
					},
					"Value" : "nonrecourse"
				},
				{
					"Region" : 
					{
						"b" : 634,
						"l" : 534,
						"r" : 634,
						"t" : 2363
					},
					"Value" : "financing"
				},
				{
					"Region" : 
					{
						"b" : 772,
						"l" : 759,
						"r" : 772,
						"t" : 2365
					},
					"Value" : "$"
				},
				{
					"Region" : 
					{
						"b" : 387,
						"l" : 282,
						"r" : 387,
						"t" : 2402
					},
					"Value" : "Recourse"
				},
				{
					"Region" : 
					{
						"b" : 1948,
						"l" : 1921,
						"r" : 1948,
						"t" : 2067
					},
					"Value" : "20"
				},
				{
					"Region" : 
					{
						"b" : 2048,
						"l" : 1986,
						"r" : 2048,
						"t" : 2067
					},
					"Value" : "Other"
				},
				{
					"Region" : 
					{
						"b" : 2178,
						"l" : 2057,
						"r" : 2178,
						"t" : 2067
					},
					"Value" : "information"
				},
				{
					"Region" : 
					{
						"b" : 2358,
						"l" : 2330,
						"r" : 2358,
						"t" : 2185
					},
					"Value" : "1,"
				},
				{
					"Region" : 
					{
						"b" : 2419,
						"l" : 2368,
						"r" : 2419,
						"t" : 2186
					},
					"Value" : "046"
				},
				{
					"Region" : 
					{
						"b" : 2419,
						"l" : 2386,
						"r" : 2419,
						"t" : 2276
					},
					"Value" : "37"
				},
				{
					"Region" : 
					{
						"b" : 2419,
						"l" : 2330,
						"r" : 2419,
						"t" : 2405
					},
					"Value" : "1,045"
				},
				{
					"Region" : 
					{
						"b" : 2440,
						"l" : 2367,
						"r" : 2440,
						"t" : 2480
					},
					"Value" : "STMT"
				},
				{
					"Region" : 
					{
						"b" : 1444,
						"l" : 1371,
						"r" : 1444,
						"t" : 2524
					},
					"Value" : "*See"
				},
				{
					"Region" : 
					{
						"b" : 1583,
						"l" : 1455,
						"r" : 1583,
						"t" : 2524
					},
					"Value" : "attached"
				},
				{
					"Region" : 
					{
						"b" : 1746,
						"l" : 1596,
						"r" : 1746,
						"t" : 2525
					},
					"Value" : "statement"
				},
				{
					"Region" : 
					{
						"b" : 1796,
						"l" : 1755,
						"r" : 1796,
						"t" : 2524
					},
					"Value" : "for"
				},
				{
					"Region" : 
					{
						"b" : 1949,
						"l" : 1806,
						"r" : 1949,
						"t" : 2524
					},
					"Value" : "additional"
				},
				{
					"Region" : 
					{
						"b" : 2137,
						"l" : 1963,
						"r" : 2137,
						"t" : 2524
					},
					"Value" : "information."
				},
				{
					"Region" : 
					{
						"b" : 0,
						"l" : -1789432832,
						"r" : 0,
						"t" : -1569715513
					},
					"Value" : ""
				},
				{
					"Region" : 
					{
						"b" : 0,
						"l" : -1789432832,
						"r" : 0,
						"t" : -1569715513
					},
					"Value" : ""
				},
				{
					"Region" : 
					{
						"b" : 0,
						"l" : -1789432832,
						"r" : 0,
						"t" : -1569715513
					},
					"Value" : ""
				},
				{
					"Region" : 
					{
						"b" : 0,
						"l" : -1789432832,
						"r" : 0,
						"t" : -1569715513
					},
					"Value" : ""
				},
				{
					"Region" : 
					{
						"b" : 0,
						"l" : -1789432832,
						"r" : 0,
						"t" : -1569715513
					},
					"Value" : ""
				},
				{
					"Region" : 
					{
						"b" : 0,
						"l" : -1789432832,
						"r" : 0,
						"t" : -1569715513
					},
					"Value" : ""
				},
				{
					"Region" : 
					{
						"b" : 0,
						"l" : -1789432832,
						"r" : 0,
						"t" : -1569715513
					},
					"Value" : ""
				},
				{
					"Region" : 
					{
						"b" : 379,
						"l" : 282,
						"r" : 379,
						"t" : 2531
					},
					"Value" : "Partner's"
				},
				{
					"Region" : 
					{
						"b" : 458,
						"l" : 387,
						"r" : 458,
						"t" : 2531
					},
					"Value" : "capital"
				},
				{
					"Region" : 
					{
						"b" : 555,
						"l" : 468,
						"r" : 555,
						"t" : 2532
					},
					"Value" : "account"
				},
				{
					"Region" : 
					{
						"b" : 659,
						"l" : 563,
						"r" : 659,
						"t" : 2531
					},
					"Value" : "analysis:"
				},
				{
					"Region" : 
					{
						"b" : 391,
						"l" : 282,
						"r" : 391,
						"t" : 2585
					},
					"Value" : "Beginning"
				},
				{
					"Region" : 
					{
						"b" : 470,
						"l" : 400,
						"r" : 470,
						"t" : 2585
					},
					"Value" : "capital"
				},
				{
					"Region" : 
					{
						"b" : 567,
						"l" : 480,
						"r" : 567,
						"t" : 2586
					},
					"Value" : "account"
				},
				{
					"Region" : 
					{
						"b" : 587,
						"l" : 584,
						"r" : 587,
						"t" : 2600
					},
					"Value" : "."
				},
				{
					"Region" : 
					{
						"b" : 772,
						"l" : 759,
						"r" : 772,
						"t" : 2583
					},
					"Value" : "$"
				},
				{
					"Region" : 
					{
						"b" : 1232,
						"l" : 1123,
						"r" : 1232,
						"t" : 2584
					},
					"Value" : "52,545"
				},
				{
					"Region" : 
					{
						"b" : 357,
						"l" : 281,
						"r" : 357,
						"t" : 2636
					},
					"Value" : "Capital"
				},
				{
					"Region" : 
					{
						"b" : 489,
						"l" : 367,
						"r" : 489,
						"t" : 2636
					},
					"Value" : "contributed"
				},
				{
					"Region" : 
					{
						"b" : 567,
						"l" : 498,
						"r" : 567,
						"t" : 2636
					},
					"Value" : "during"
				},
				{
					"Region" : 
					{
						"b" : 610,
						"l" : 576,
						"r" : 610,
						"t" : 2636
					},
					"Value" : "the"
				},
				{
					"Region" : 
					{
						"b" : 667,
						"l" : 618,
						"r" : 667,
						"t" : 2640
					},
					"Value" : "year"
				},
				{
					"Region" : 
					{
						"b" : 772,
						"l" : 759,
						"r" : 772,
						"t" : 2634
					},
					"Value" : "$"
				},
				{
					"Region" : 
					{
						"b" : 1233,
						"l" : 1180,
						"r" : 1233,
						"t" : 2634
					},
					"Value" : "111"
				},
				{
					"Region" : 
					{
						"b" : 364,
						"l" : 281,
						"r" : 364,
						"t" : 2687
					},
					"Value" : "Current"
				},
				{
					"Region" : 
					{
						"b" : 420,
						"l" : 371,
						"r" : 420,
						"t" : 2691
					},
					"Value" : "year"
				},
				{
					"Region" : 
					{
						"b" : 522,
						"l" : 429,
						"r" : 522,
						"t" : 2687
					},
					"Value" : "increase"
				},
				{
					"Region" : 
					{
						"b" : 649,
						"l" : 531,
						"r" : 649,
						"t" : 2686
					},
					"Value" : "(decrease)"
				},
				{
					"Region" : 
					{
						"b" : 662,
						"l" : 659,
						"r" : 662,
						"t" : 2702
					},
					"Value" : "."
				},
				{
					"Region" : 
					{
						"b" : 772,
						"l" : 759,
						"r" : 772,
						"t" : 2685
					},
					"Value" : "$"
				},
				{
					"Region" : 
					{
						"b" : 1231,
						"l" : 1123,
						"r" : 1231,
						"t" : 2685
					},
					"Value" : "11,438"
				},
				{
					"Region" : 
					{
						"b" : 418,
						"l" : 280,
						"r" : 418,
						"t" : 2738
					},
					"Value" : "Withdrawals"
				},
				{
					"Region" : 
					{
						"b" : 442,
						"l" : 426,
						"r" : 442,
						"t" : 2738
					},
					"Value" : "&"
				},
				{
					"Region" : 
					{
						"b" : 583,
						"l" : 449,
						"r" : 583,
						"t" : 2738
					},
					"Value" : "distributions"
				},
				{
					"Region" : 
					{
						"b" : 793,
						"l" : 759,
						"r" : 793,
						"t" : 2733
					},
					"Value" : "$("
				},
				{
					"Region" : 
					{
						"b" : 1231,
						"l" : 1122,
						"r" : 1231,
						"t" : 2737
					},
					"Value" : "20,374"
				},
				{
					"Region" : 
					{
						"b" : 357,
						"l" : 282,
						"r" : 357,
						"t" : 2789
					},
					"Value" : "Ending"
				},
				{
					"Region" : 
					{
						"b" : 437,
						"l" : 366,
						"r" : 437,
						"t" : 2789
					},
					"Value" : "capital"
				},
				{
					"Region" : 
					{
						"b" : 533,
						"l" : 447,
						"r" : 533,
						"t" : 2790
					},
					"Value" : "account"
				},
				{
					"Region" : 
					{
						"b" : 546,
						"l" : 543,
						"r" : 546,
						"t" : 2804
					},
					"Value" : "."
				},
				{
					"Region" : 
					{
						"b" : 772,
						"l" : 759,
						"r" : 772,
						"t" : 2787
					},
					"Value" : "$"
				},
				{
					"Region" : 
					{
						"b" : 1231,
						"l" : 1122,
						"r" : 1231,
						"t" : 2788
					},
					"Value" : "43,720"
				},
				{
					"Region" : 
					{
						"b" : 364,
						"l" : 273,
						"r" : 364,
						"t" : 2868
					},
					"Value" : "EITax"
				},
				{
					"Region" : 
					{
						"b" : 429,
						"l" : 373,
						"r" : 429,
						"t" : 2877
					},
					"Value" : "basis"
				},
				{
					"Region" : 
					{
						"b" : 653,
						"l" : 538,
						"r" : 653,
						"t" : 2868
					},
					"Value" : "EIGAAP"
				},
				{
					"Region" : 
					{
						"b" : 905,
						"l" : 776,
						"r" : 905,
						"t" : 2868
					},
					"Value" : "|:|Section"
				},
				{
					"Region" : 
					{
						"b" : 986,
						"l" : 914,
						"r" : 986,
						"t" : 2876
					},
					"Value" : "704(b)"
				},
				{
					"Region" : 
					{
						"b" : 1048,
						"l" : 995,
						"r" : 1048,
						"t" : 2877
					},
					"Value" : "book"
				},
				{
					"Region" : 
					{
						"b" : 386,
						"l" : 273,
						"r" : 386,
						"t" : 2919
					},
					"Value" : "DOther"
				},
				{
					"Region" : 
					{
						"b" : 489,
						"l" : 394,
						"r" : 489,
						"t" : 2925
					},
					"Value" : "(explain)"
				},
				{
					"Region" : 
					{
						"b" : 316,
						"l" : 282,
						"r" : 316,
						"t" : 3009
					},
					"Value" : "Did"
				},
				{
					"Region" : 
					{
						"b" : 359,
						"l" : 325,
						"r" : 359,
						"t" : 3009
					},
					"Value" : "the"
				},
				{
					"Region" : 
					{
						"b" : 447,
						"l" : 369,
						"r" : 447,
						"t" : 3010
					},
					"Value" : "partner"
				},
				{
					"Region" : 
					{
						"b" : 564,
						"l" : 455,
						"r" : 564,
						"t" : 3009
					},
					"Value" : "contribute"
				},
				{
					"Region" : 
					{
						"b" : 664,
						"l" : 574,
						"r" : 664,
						"t" : 3010
					},
					"Value" : "property"
				},
				{
					"Region" : 
					{
						"b" : 714,
						"l" : 671,
						"r" : 714,
						"t" : 3009
					},
					"Value" : "with"
				},
				{
					"Region" : 
					{
						"b" : 736,
						"l" : 723,
						"r" : 736,
						"t" : 3013
					},
					"Value" : "a"
				},
				{
					"Region" : 
					{
						"b" : 817,
						"l" : 745,
						"r" : 817,
						"t" : 3009
					},
					"Value" : "built-in"
				},
				{
					"Region" : 
					{
						"b" : 872,
						"l" : 826,
						"r" : 872,
						"t" : 3009
					},
					"Value" : "gain"
				},
				{
					"Region" : 
					{
						"b" : 904,
						"l" : 881,
						"r" : 904,
						"t" : 3013
					},
					"Value" : "or"
				},
				{
					"Region" : 
					{
						"b" : 968,
						"l" : 912,
						"r" : 968,
						"t" : 3009
					},
					"Value" : "loss?"
				},
				{
					"Region" : 
					{
						"b" : 366,
						"l" : 273,
						"r" : 366,
						"t" : 3053
					},
					"Value" : "DYes"
				},
				{
					"Region" : 
					{
						"b" : 618,
						"l" : 538,
						"r" : 618,
						"t" : 3053
					},
					"Value" : "END"
				},
				{
					"Region" : 
					{
						"b" : 337,
						"l" : 325,
						"r" : 337,
						"t" : 3098
					},
					"Value" : "If"
				},
				{
					"Region" : 
					{
						"b" : 410,
						"l" : 344,
						"r" : 410,
						"t" : 3098
					},
					"Value" : "“Yes“,"
				},
				{
					"Region" : 
					{
						"b" : 485,
						"l" : 419,
						"r" : 485,
						"t" : 3098
					},
					"Value" : "attach"
				},
				{
					"Region" : 
					{
						"b" : 603,
						"l" : 495,
						"r" : 603,
						"t" : 3099
					},
					"Value" : "statement"
				},
				{
					"Region" : 
					{
						"b" : 659,
						"l" : 612,
						"r" : 659,
						"t" : 3097
					},
					"Value" : "(see"
				},
				{
					"Region" : 
					{
						"b" : 802,
						"l" : 668,
						"r" : 802,
						"t" : 3097
					},
					"Value" : "instructions)"
				},
				{
					"Region" : 
					{
						"b" : 2436,
						"l" : 2207,
						"r" : 2436,
						"t" : 103
					},
					"Value" : "bElllB\n\n"
				},
				{
					"Region" : 
					{
						"b" : 1586,
						"l" : 1421,
						"r" : 1586,
						"t" : 151
					},
					"Value" : "D Final K1\n\n"
				},
				{
					"Region" : 
					{
						"b" : 1977,
						"l" : 1761,
						"r" : 1977,
						"t" : 151
					},
					"Value" : "D Amended K-1\n\n"
				},
				{
					"Region" : 
					{
						"b" : 2440,
						"l" : 2154,
						"r" : 2440,
						"t" : 161
					},
					"Value" : "OMB No. 1545-0099\n\n"
				},
				{
					"Region" : 
					{
						"b" : 442,
						"l" : 172,
						"r" : 442,
						"t" : 207
					},
					"Value" : "Schedule K-1\n\n"
				},
				{
					"Region" : 
					{
						"b" : 1245,
						"l" : 1010,
						"r" : 1245,
						"t" : 201
					},
					"Value" : "3313\n\n"
				},
				{
					"Region" : 
					{
						"b" : 417,
						"l" : 173,
						"r" : 417,
						"t" : 255
					},
					"Value" : "(Form 1065)\n\n"
				},
				{
					"Region" : 
					{
						"b" : 474,
						"l" : 169,
						"r" : 474,
						"t" : 323
					},
					"Value" : "Department of the Treasury\n\n"
				},
				{
					"Region" : 
					{
						"b" : 1127,
						"l" : 706,
						"r" : 1127,
						"t" : 306
					},
					"Value" : "For calendar year 2013, or tax\n\n"
				},
				{
					"Region" : 
					{
						"b" : 450,
						"l" : 170,
						"r" : 450,
						"t" : 355
					},
					"Value" : "Internal Revenue Service\n\n"
				},
				{
					"Region" : 
					{
						"b" : 1313,
						"l" : 1229,
						"r" : 1313,
						"t" : 361
					},
					"Value" : ".2013\n\n"
				},
				{
					"Region" : 
					{
						"b" : 908,
						"l" : 704,
						"r" : 908,
						"t" : 361
					},
					"Value" : "year beginning\n\n"
				},
				{
					"Region" : 
					{
						"b" : 960,
						"l" : 868,
						"r" : 960,
						"t" : 413
					},
					"Value" : "ending\n\n"
				},
				{
					"Region" : 
					{
						"b" : 1153,
						"l" : 1104,
						"r" : 1153,
						"t" : 413
					},
					"Value" : ",20\n\n"
				},
				{
					"Region" : 
					{
						"b" : 1040,
						"l" : 174,
						"r" : 1040,
						"t" : 487
					},
					"Value" : "Partner's Share of Income, Deductions,\n\n"
				},
				{
					"Region" : 
					{
						"b" : 436,
						"l" : 173,
						"r" : 436,
						"t" : 539
					},
					"Value" : "Credits, etc.\n\n"
				},
				{
					"Region" : 
					{
						"b" : 1256,
						"l" : 627,
						"r" : 1256,
						"t" : 546
					},
					"Value" : "> See back of form and separate instructions.\n\n"
				},
				{
					"Region" : 
					{
						"b" : 223,
						"l" : 214,
						"r" : 223,
						"t" : 613
					},
					"Value" : "I\n\n"
				},
				{
					"Region" : 
					{
						"b" : 988,
						"l" : 169,
						"r" : 988,
						"t" : 3152
					},
					"Value" : "For Papenuork Reduction Act Notice, see Instructions for Form 1065.\n\n"
				},
				{
					"Region" : 
					{
						"b" : 1535,
						"l" : 1269,
						"r" : 1535,
						"t" : 3150
					},
					"Value" : "IRS . gov/form1065\n\n"
				},
				{
					"Region" : 
					{
						"b" : 1954,
						"l" : 1768,
						"r" : 1954,
						"t" : 3152
					},
					"Value" : "Cat. No. 11394R\n\n"
				},
				{
					"Region" : 
					{
						"b" : 2442,
						"l" : 2072,
						"r" : 2442,
						"t" : 3151
					},
					"Value" : "Schedule K-1 (Form 1065) 2013\n\n"
				}
			]
		}
	]
}